setup.py
sqlsession/__init__.py
sqlsession.egg-info/PKG-INFO
sqlsession.egg-info/SOURCES.txt
sqlsession.egg-info/dependency_links.txt
sqlsession.egg-info/not-zip-safe
sqlsession.egg-info/requires.txt
sqlsession.egg-info/top_level.txt
test/test.py