Metadata-Version: 2.1
Name: sqlsession
Version: 0.1.51
Summary: Dirt simple CRUD API to access SQL databases
Home-page: https://github.com/spookyowl/sqlsession
Author: Peter Facka
Author-email: pfacka@trackingwire.com
License: MIT Licence (http://opensource.org/licenses/MIT)
Classifier: Development Status :: 3 - Alpha
Classifier: Environment :: Web Environment
Classifier: Intended Audience :: Developers
Classifier: Operating System :: Microsoft :: Windows
Classifier: Operating System :: MacOS :: MacOS X
Classifier: Operating System :: POSIX
Classifier: Programming Language :: Python :: 3.10
Classifier: License :: OSI Approved :: MIT License
Provides: sqlsession
